Metadata-Version: 2.1
Name: libalisson
Version: 0.2
Summary: modulo para exemplificar construção de projetos python no curso pytools
Home-page: https://github.com/AlissonLGoncalves/libalisson
Author: Alisson Luiz Gonçalves
Author-email: alisson.16lg@gmail.com
License: LICENSE
Platform: UNKNOWN
Classifier: Development Status :: 2 - Pre-Alpha
Classifier: Environment :: Console
Classifier: Intended Audience :: Developers
Classifier: License :: OSI Approved :: GNU Affero General Public License v3 or later (AGPLv3+)
Classifier: Operating System :: OS Independent
Classifier: Programming Language :: Python :: 3.10
Classifier: Framework :: Pytest
License-File: LICENSE
